zapv2/__init__.py
zapv2/accessControl.py
zapv2/acsrf.py
zapv2/ajaxSpider.py
zapv2/alert.py
zapv2/alertFilter.py
zapv2/ascan.py
zapv2/authentication.py
zapv2/authorization.py
zapv2/automation.py
zapv2/autoupdate.py
zapv2/brk.py
zapv2/context.py
zapv2/core.py
zapv2/custompayloads.py
zapv2/exim.py
zapv2/forcedUser.py
zapv2/graphql.py
zapv2/httpSessions.py
zapv2/localProxies.py
zapv2/network.py
zapv2/openapi.py
zapv2/params.py
zapv2/pnh.py
zapv2/pscan.py
zapv2/replacer.py
zapv2/reports.py
zapv2/retest.py
zapv2/reveal.py
zapv2/revisit.py
zapv2/ruleConfig.py
zapv2/script.py
zapv2/search.py
zapv2/selenium.py
zapv2/sessionManagement.py
zapv2/soap.py
zapv2/spider.py
zapv2/stats.py
zapv2/users.py
zapv2/wappalyzer.py
zapv2/websocket.py
zaproxy-0.3.0.dist-info/LICENSE
zaproxy-0.3.0.dist-info/METADATA
zaproxy-0.3.0.dist-info/WHEEL
zaproxy-0.3.0.dist-info/RECORD
