Metadata-Version: 2.1
Name: zaproxy
Version: 0.3.0
Summary: ZAP API Client
Home-page: https://www.zaproxy.org/
License: Apache-2.0
Author: ZAP Development Team
Author-email: zaproxy-develop@googlegroups.com
Requires-Python: >=3.8,<4.0
Classifier: Development Status :: 5 - Production/Stable
Classifier: Intended Audience :: Developers
Classifier: Intended Audience :: Information Technology
Classifier: License :: OSI Approved :: Apache Software License
Classifier: Programming Language :: Python :: 3
Classifier: Programming Language :: Python :: 3.8
Classifier: Programming Language :: Python :: 3.9
Classifier: Programming Language :: Python :: 3.10
Classifier: Programming Language :: Python :: 3.11
Classifier: Programming Language :: Python :: 3.12
Classifier: Topic :: Security
Classifier: Topic :: Software Development :: Libraries :: Python Modules
Requires-Dist: requests (>=2.31.0,<3.0.0)
Requires-Dist: six (>=1.16.0,<2.0.0)
Project-URL: Documentation, https://www.zaproxy.org/docs/api/
Project-URL: Repository, https://github.com/zaproxy/zap-api-python.git
